setup.py
bin/replayer
replayer/__init__.py
replayer/block_cookie_policy.py
replayer/config_constants.py
replayer/config_reader.py
replayer/http_worker.py
replayer/inspector.py
replayer/log_constants.py
replayer/log_worker.py
replayer/url_builder.py
replayer/url_filter.py
replayer.egg-info/PKG-INFO
replayer.egg-info/SOURCES.txt
replayer.egg-info/dependency_links.txt
replayer.egg-info/not-zip-safe
replayer.egg-info/requires.txt
replayer.egg-info/top_level.txt