Metadata-Version: 1.1
Name: replayer
Version: 0.5.4
Summary: Replay easily an Apache access.log
Home-page: https://github.com/buechele/replayer
Author: Andreas Buechele
Author-email: andreas@buechele.org
License: MIT
Platform: any
Classifier: Development Status :: 4 - Beta
Classifier: Environment :: Console
Classifier: Intended Audience :: System Administrators
Classifier: License :: OSI Approved :: MIT License
Classifier: Natural Language :: English
Classifier: Operating System :: OS Independent
Classifier: Programming Language :: Python :: 2.7
Classifier: Topic :: System :: Systems Administration
